setup.py
shinkenplugins/__init__.py
shinkenplugins.plugins.postgresql_lag.egg-info/PKG-INFO
shinkenplugins.plugins.postgresql_lag.egg-info/SOURCES.txt
shinkenplugins.plugins.postgresql_lag.egg-info/dependency_links.txt
shinkenplugins.plugins.postgresql_lag.egg-info/entry_points.txt
shinkenplugins.plugins.postgresql_lag.egg-info/namespace_packages.txt
shinkenplugins.plugins.postgresql_lag.egg-info/requires.txt
shinkenplugins.plugins.postgresql_lag.egg-info/top_level.txt
shinkenplugins/plugins/__init__.py
shinkenplugins/plugins/postgresql_lag/__init__.py
shinkenplugins/plugins/postgresql_lag/postgresql_lag.py